{
    "id": "1558a0c1-ac28-45da-ba04-42e750d37013",
    "integration_id": "80a5b997-fb5d-452e-ab29-b333a7f9253d",
    "content": {
        "parameters": [
            {
                "meta": {
                    "config": {
                        "url": "/ORACLE?current_page=1&page_size=999",
                        "method": "get",
                        "urlType": "secret",
                        "labelKey": "name",
                        "valueKey": "_id"
                    },
                    "options": [],
                    "htmlProps": {
                        "showAddNew": true
                    },
                    "validation": {
                        "required": true
                    },
                    "description": "Oracle Database is a powerful, enterprise-grade relational database management system developed by Oracle Corporation",
                    "displayName": "Oracle connection",
                    "displayType": "autocomplete",
                    "placeholder": "Select connection"
                },
                "name": "secret"
            },
            {
                "meta": {
                    "value": "",
                    "options": [
                        {
                            "label": "Database Operation",
                            "value": "operation",
                            "description": "Execute SELECT queries to read data from Oracle database."
                        }
                    ],
                    "validation": {
                        "required": true
                    },
                    "description": "Select the resource you want to work with.",
                    "displayName": "Resource",
                    "displayType": "select",
                    "placeholder": "Select a resource",
                    "dependencies": {
                        "conditions": [
                            {
                                "field": "secret",
                                "operator": "NOT_EMPTY"
                            }
                        ]
                    }
                },
                "name": "resource"
            }
        ]
    },
    "created_by": "00000000000000000000000000000000eabe80b1f89dc01f3f7d24b69c949006",
    "modified_by": "00000000000000000000000000000000eabe80b1f89dc01f3f7d24b69c949006",
    "created_at": "2025-06-11T12:12:16.182Z",
    "updated_at": "2025-06-11T12:12:16.182Z"
}
