{
    "name": "Zendesk_Talk",
    "slug": "blt-int.zendesk-talk",
    "description": {
        "trigger": "",
        "integration": "Create and manage Zendesk Talk calls, voice interactions, and call analytics directly from your workflows. Automate call handling, routing, and voice communication to streamline customer support operations and improve call center efficiency."
    },
    "icon": "https://www.svgviewer.dev/static-svgs/34347/zendesk.svg",
    "activity_type": "customActivity",
    "trigger_type": null,
    "meta": {
        "ai_description": {
            "trigger": "",
            "integration": "Enables automated creation and management of Zendesk Talk calls, voice interactions, and call analytics within workflows. Streamlines call center processes by leveraging AI to trigger, route, or manage calls and analyze voice communication based on workflow events."
        }
    }
}
