{
    "id": "8a866186-d1bc-4b06-b4a4-6fef00c08fe2",
    "documentation": "## Catalog Cloud Authentication\n\n### Prerequisites\n\n-   Create a Catalog Cloud account.\n\n### Supported Authentication Methods\n\n-   API key\n\n\n### Related Resources\n\nRefer to [Catalog Cloud documentation](https://docs.pim.fynd.com/documentation) for more information about the different features and services.\n\n### Using API Key\n\nTo configure this secret, you'll need:\n\n1. **API token**: Refer to the [Catalog Cloud API token documentation](https://docs.pim.fynd.com/documentation/docs/manage-account#token) for detailed instructions on getting your API key.\n",
    "integration_id": "17c6bcc4-bf7f-4567-99b0-cabb4f13b619",
    "content": {
        "api_key": {
            "parameters": [
                {
                    "meta": {
                        "validation": {
                            "required": true
                        },
                        "description": "Please go to tokens page on Catalog Cloud console to get API token.",
                        "displayName": "API Key",
                        "displayType": "password",
                        "placeholder": "Enter API Key"
                    },
                    "name": "api_key"
                }
            ]
        },
        "parameters": [
            {
                "meta": {
                    "options": [
                        {
                            "label": "API Key",
                            "value": "api_key"
                        }
                    ],
                    "validation": {
                        "required": true
                    },
                    "description": "Choose the type of authentication you want to use.",
                    "displayName": "Authentication Type",
                    "displayType": "select",
                    "placeholder": "Select an authentication type"
                },
                "name": "type"
            }
        ]
    },
    "created_by": "00000000000000000000000000000000eabe80b1f89dc01f3f7d24b69c949006",
    "modified_by": "00000000000000000000000000000000eabe80b1f89dc01f3f7d24b69c949006",
    "created_at": "2025-06-11T12:12:26.332Z",
    "updated_at": "2025-06-11T12:12:26.332Z"
}
