{
    "api_key": {
        "validate": {
            "url": "https://api.linkedin.com/v2/userinfo",
            "method": "get",
            "headers": {
                "Content-Type": "application/json",
                "Authorization": "Bearer {{secrets.api_token}}"
            },
            "response": {
                "error": {
                    "code": "{{response.status}}",
                    "message": "{{response.data.message}}"
                },
                "output": "{{response.data}}"
            }
        },
        "parameters": [
            {
                "meta": {
                    "validation": {
                        "required": true,
                        "requiredDetail": {
                            "errorMsg": "Please add the API key as it cannot be empty"
                        }
                    },
                    "description": "Your Linkedin API Key. Navigate to the <a href='https://www.linkedin.com/developers/tools/oauth/token-generator?clientId=77klpugw1fujy1' target='_blank'> LinkedIn API documentation </a> for more details.",
                    "displayName": "API Key",
                    "displayType": "password",
                    "placeholder": "Enter API Key",
                    "dependencies": {
                        "conditions": [
                            {
                                "field": "type",
                                "value": "api_key",
                                "operator": "EQUALS"
                            }
                        ]
                    }
                },
                "name": "api_token"
            }
        ]
    },
    "parameters": [
        {
            "meta": {
                "value": "api_key",
                "options": [
                    {
                        "label": "API Key",
                        "value": "api_key"
                    }
                ],
                "validation": {
                    "required": true,
                    "requiredDetail": {
                        "errorMsg": "Please select the Authentication type as it cannot be empty"
                    }
                },
                "description": "Choose the type of authentication you want to use.",
                "displayName": "Authentication Type",
                "displayType": "select",
                "placeholder": "Select an authentication type"
            },
            "name": "type"
        }
    ]
}
