{
    "parameters": [
        {
            "meta": {
                "options": [
                    {
                        "label": "Search Tax Classes",
                        "value": "taxClasses.searchTaxClasses",
                        "description": "Search for specific tax classes."
                    },
                    {
                        "label": "Get Tax Class by ID",
                        "value": "taxClasses.getTaxClassById",
                        "description": "Retrieve a specific tax class by its ID."
                    }
                ],
                "validation": {
                    "required": true
                },
                "description": "Select the operation you want to perform.",
                "displayName": "Operation",
                "displayType": "select",
                "placeholder": "Select an operation",
                "dependencies": {
                    "conditions": [
                        {
                            "field": "resource",
                            "value": "taxClasses",
                            "operator": "EQUALS"
                        }
                    ]
                }
            },
            "name": "operation"
        }
    ],
    "getTaxClasses": {
        "definition": {
            "url": "https://{{secrets.domain}}/rest/default/V1/taxClasses",
            "method": "get",
            "headers": {
                "Authorization": "Bearer {{secrets.access_token}}"
            },
            "response": {
                "error": {
                    "code": "{{response.status}}",
                    "message": "{{response.data.message}}"
                },
                "output": "{{response.data}}"
            }
        },
        "parameters": []
    },
    "getTaxClassByTaxClassId": {
        "definition": {
            "url": "https://{{secrets.domain}}/rest/default/V1/taxClasses/{taxClassId}",
            "method": "get",
            "headers": {
                "Authorization": "Bearer {{secrets.access_token}}"
            },
            "response": {
                "error": {
                    "code": "{{response.status}}",
                    "message": "{{response.data.message}}"
                },
                "output": "{{response.data}}"
            }
        },
        "parameters": []
    },
    "id": "da473dd2-e815-48ed-b12e-4d360e2298b0",
    "integration_id": "edeb3598-38fd-40ea-b38f-ece3e1e6f1f3",
    "resource_id": "4a8d1531-b825-4d28-9862-bcbb8a5528dd",
    "name": "sendEmail",
    "content": {
        "definition": {
            "url": "https://{{secrets.domain}}/rest/default/V1/shipment/{{parameters.id}}/emails",
            "body": {
                "email": "{{parameters.email}}"
            },
            "method": "post",
            "headers": {
                "Authorization": "Bearer {{secrets.access_token}}"
            },
            "response": {
                "error": {
                    "code": "{{response.status}}",
                    "message": "{{response.data.message}}"
                },
                "output": "{{response.data}}"
            }
        },
        "parameters": [
            {
                "meta": {
                    "validation": {
                        "required": true
                    },
                    "description": "The ID of the shipment to send an email for.",
                    "displayName": "Shipment ID",
                    "displayType": "text",
                    "placeholder": "Enter the shipment ID"
                },
                "name": "id"
            },
            {
                "meta": {
                    "validation": {
                        "required": true
                    },
                    "description": "The email address to send the shipment details to.",
                    "displayName": "Email",
                    "displayType": "text",
                    "placeholder": "Enter the email address"
                },
                "name": "email"
            }
        ]
    },
    "created_by": "ruchivishwakarma@fynd-external.com",
    "modified_by": "ruchivishwakarma@fynd-external.com",
    "created_at": "2025-06-17T04:52:46.306Z",
    "updated_at": "2025-06-17T13:39:54.101Z"
}
